letta_client/__init__.py
letta_client/_base_client.py
letta_client/_client.py
letta_client/_compat.py
letta_client/_constants.py
letta_client/_exceptions.py
letta_client/_files.py
letta_client/_models.py
letta_client/_qs.py
letta_client/_resource.py
letta_client/_response.py
letta_client/_streaming.py
letta_client/_types.py
letta_client/_version.py
letta_client/pagination.py
letta_client/py.typed
letta_client/_utils/__init__.py
letta_client/_utils/_compat.py
letta_client/_utils/_datetime_parse.py
letta_client/_utils/_json.py
letta_client/_utils/_logs.py
letta_client/_utils/_proxy.py
letta_client/_utils/_reflection.py
letta_client/_utils/_resources_proxy.py
letta_client/_utils/_streams.py
letta_client/_utils/_sync.py
letta_client/_utils/_transform.py
letta_client/_utils/_typing.py
letta_client/_utils/_utils.py
letta_client/lib/.keep
letta_client/resources/__init__.py
letta_client/resources/access_tokens.py
letta_client/resources/messages.py
letta_client/resources/passages.py
letta_client/resources/tags.py
letta_client/resources/tools.py
letta_client/resources/agents/__init__.py
letta_client/resources/agents/agents.py
letta_client/resources/agents/archives.py
letta_client/resources/agents/blocks.py
letta_client/resources/agents/files.py
letta_client/resources/agents/folders.py
letta_client/resources/agents/identities.py
letta_client/resources/agents/messages.py
letta_client/resources/agents/passages.py
letta_client/resources/agents/schedule.py
letta_client/resources/agents/tools.py
letta_client/resources/archives/__init__.py
letta_client/resources/archives/archives.py
letta_client/resources/archives/passages.py
letta_client/resources/blocks/__init__.py
letta_client/resources/blocks/agents.py
letta_client/resources/blocks/blocks.py
letta_client/resources/conversations/__init__.py
letta_client/resources/conversations/conversations.py
letta_client/resources/conversations/messages.py
letta_client/resources/folders/__init__.py
letta_client/resources/folders/agents.py
letta_client-1.7.7.dist-info/METADATA
letta_client-1.7.7.dist-info/WHEEL
letta_client-1.7.7.dist-info/licenses/LICENSE
letta_client-1.7.7.dist-info/RECORD
